uscpi/__init__.py
uscpi/client.py
uscpi/instrument.py
uscpi/protocol.py
uscpi-0.3.0.dist-info/LICENSE
uscpi-0.3.0.dist-info/METADATA
uscpi-0.3.0.dist-info/WHEEL
uscpi-0.3.0.dist-info/top_level.txt
uscpi-0.3.0.dist-info/RECORD
