Metadata-Version: 2.1
Name: uscpi
Version: 0.3.0
Summary: An asynchronous SCPI instrumentation library.
Author-email: Michael Czigler <michaelczigler@icloud.com>
License: BSD 3-Clause License
Project-URL: homepage, https://github.com/mcpcpc/uscpi
Project-URL: repository, https://github.com/mcpcpc/uscpi
Keywords: instrumentation,SCPI,asynchronous
Classifier: Development Status :: 5 - Production/Stable
Classifier: License :: OSI Approved :: BSD License
Classifier: Operating System :: Microsoft :: Windows
Classifier: Operating System :: POSIX :: Linux
Classifier: Operating System :: MacOS :: MacOS X
Classifier: Programming Language :: Python
Requires-Python: >=3.11
License-File: LICENSE
Provides-Extra: dev
Requires-Dist: coverage ; extra == 'dev'
Requires-Dist: black ; extra == 'dev'
